PandaConfig/__init__.py
PandaConfig/config.py
PandaConfig/default_func.py
PandaConfig/loader.py
PandaConfig/resolver.py
nguyenpanda_config-0.1.1.dist-info/licenses/LICENSE.txt
nguyenpanda_config-0.1.1.dist-info/METADATA
nguyenpanda_config-0.1.1.dist-info/WHEEL
nguyenpanda_config-0.1.1.dist-info/top_level.txt
nguyenpanda_config-0.1.1.dist-info/RECORD
