Metadata-Version: 2.4
Name: nguyenpanda-config
Version: 0.1.1
Summary: A dynamic YAML configuration engine supporting variable interpolation, function calls, and file inheritance.
Author-email: Tuong Nguyen Ha <hatuongnguyen@0107gmail.com>
License: MIT
Project-URL: Homepage, https://github.com/nguyenpanda/PandaConfig
Project-URL: Documentation, https://nguyenpanda.github.io/PandaConfig/
Project-URL: Source, https://github.com/nguyenpanda/PandaConfig
Requires-Python: >=3.10
License-File: LICENSE.txt
Requires-Dist: nguyenpanda>=1.0.0
Requires-Dist: pyyaml>=6.0.3
Dynamic: license-file
